spyn/__init__.py
spyn/util.py
spyn/ppi/__init__.py
spyn/ppi/binary_pairs_kv.py
spyn/ppi/markov.py
spyn/ppi/naive_bayes_graph.py
spyn/ppi/pairs_pot.py
spyn/ppi/pot.py
spyn/ppi/potter.py
spyn/ppi/old/__init__.py
spyn/ppi/old/naive_binary_network.py
spyn/ppi/pstan/__init__.py
spyn/ppi/pstan/io.py
spyn/ppi/pstan/models_scripts/__init__.py
spyn/ppi/pstan/models_scripts/mixture_of_two_binomials.py
spyn/utils/__init__.py
spyn/utils/color.py
spyn/utils/daf.py
spyn/utils/order_conserving.py
spyn/utils/ordered_set.py
spyn/utils/special.py
spyn-0.0.6.dist-info/LICENSE
spyn-0.0.6.dist-info/METADATA
spyn-0.0.6.dist-info/WHEEL
spyn-0.0.6.dist-info/top_level.txt
spyn-0.0.6.dist-info/RECORD
