Metadata-Version: 2.1
Name: spyn
Version: 0.0.6
Summary: Tools to transform data into "model-less" operable inference objects
Home-page: https://github.com/thorwhalen/spyn
Author: Thor Whalen
License: mit
Keywords: machine learning,artificial intelligence,AI,ML,probabilistic inference,Bayesian
Platform: any
Classifier: Intended Audience :: Developers
Classifier: Topic :: Software Development
Classifier: License :: OSI Approved :: Apache Software License
Classifier: Programming Language :: Python :: 3.8
Requires-Dist: matplotlib
Requires-Dist: numpy
Requires-Dist: pandas
